LICENSE
MANIFEST.in
README.rst
setup.py
django_ohm2_backoffice_light.egg-info/PKG-INFO
django_ohm2_backoffice_light.egg-info/SOURCES.txt
django_ohm2_backoffice_light.egg-info/dependency_links.txt
django_ohm2_backoffice_light.egg-info/requires.txt
django_ohm2_backoffice_light.egg-info/top_level.txt
docs/INFO.txt
ohm2_backoffice_light/__init__.py
ohm2_backoffice_light/admin.py
ohm2_backoffice_light/apps.py
ohm2_backoffice_light/context_processors.py
ohm2_backoffice_light/decorators.py
ohm2_backoffice_light/definitions.py
ohm2_backoffice_light/dispatcher.py
ohm2_backoffice_light/errors.py
ohm2_backoffice_light/managers.py
ohm2_backoffice_light/middlewares.py
ohm2_backoffice_light/models.py
ohm2_backoffice_light/serializers.py
ohm2_backoffice_light/settings.py
ohm2_backoffice_light/tests.py
ohm2_backoffice_light/urls.py
ohm2_backoffice_light/utils.py
ohm2_backoffice_light/views.py
ohm2_backoffice_light/api/v1/dispatcher.py
ohm2_backoffice_light/api/v1/errors.py
ohm2_backoffice_light/api/v1/urls.py
ohm2_backoffice_light/api/v1/views.py
ohm2_backoffice_light/api/v1/__pycache__/dispatcher.cpython-35.pyc
ohm2_backoffice_light/api/v1/__pycache__/errors.cpython-35.pyc
ohm2_backoffice_light/api/v1/__pycache__/urls.cpython-35.pyc
ohm2_backoffice_light/api/v1/__pycache__/views.cpython-35.pyc
ohm2_backoffice_light/management/.DS_Store
ohm2_backoffice_light/management/__init__.py
ohm2_backoffice_light/management/__pycache__/__init__.cpython-35.pyc
ohm2_backoffice_light/management/commands/__init__.py
ohm2_backoffice_light/management/commands/ohm2_backoffice_light_create_staff_user.py
ohm2_backoffice_light/management/commands/ohm2_backoffice_light_test_command.py
ohm2_backoffice_light/management/commands/__pycache__/__init__.cpython-35.pyc
ohm2_backoffice_light/management/commands/__pycache__/ohm2_backoffice_light_create_staff_user.cpython-35.pyc
ohm2_backoffice_light/migrations/0001_initial.py
ohm2_backoffice_light/migrations/__init__.py
ohm2_backoffice_light/migrations/__pycache__/0001_initial.cpython-35.pyc
ohm2_backoffice_light/migrations/__pycache__/__init__.cpython-35.pyc