Metadata-Version: 1.1
Name: django-ohm2-backoffice-light
Version: 0.2.4
Summary: Django application to easily handle addresses
Home-page: http://www.ohm2.cl/
Author: Oliver Herrera
Author-email: oliver@ohm2.cl
License: BSD License
Platform: UNKNOWN
Classifier: Environment :: Web Environment
Classifier: Framework :: Django
Classifier: Intended Audience :: Developers
Classifier: License :: OSI Approved :: BSD License
Classifier: Operating System :: OS Independent
Classifier: Programming Language :: Python :: 3.3
Classifier: Programming Language :: Python :: 3.4
Classifier: Programming Language :: Python :: 3.5
Classifier: Topic :: Internet :: WWW/HTTP
Classifier: Topic :: Internet :: WWW/HTTP :: Dynamic Content
